logather/__init__.py
logather/__main__.py
logather/cmdline.py
logather/log_regexps.py
logather/logather.py
logather/startpage.py
logather/tor_proxies.py
logather/validator.py
logather-0.0.2a0.dist-info/LICENSE
logather-0.0.2a0.dist-info/METADATA
logather-0.0.2a0.dist-info/WHEEL
logather-0.0.2a0.dist-info/top_level.txt
logather-0.0.2a0.dist-info/RECORD
