Metadata-Version: 2.1
Name: logather
Version: 0.0.2a0
Summary: Public HTTP log gatherer tool
Home-page: https://github.com/mtnalonso/logather
Author: Martin Alonso Vilar
Author-email: mtnalonso@protonmail.com
License: GNU General Public License v3 (GPLv3)
Platform: UNKNOWN
Classifier: Development Status :: 2 - Pre-Alpha
Classifier: Environment :: Console
Classifier: Intended Audience :: Developers
Classifier: License :: OSI Approved :: GNU General Public License v3 (GPLv3)
Classifier: Operating System :: POSIX :: Linux
Classifier: Programming Language :: Python :: 3.8
Classifier: Programming Language :: Python :: Implementation :: PyPy
Classifier: Topic :: Software Development :: Libraries :: Python Modules
Requires-Python: >=3.8
Requires-Dist: requests
Requires-Dist: pysocks
Requires-Dist: beautifulsoup4
